tokmor_pos/__init__.py
tokmor_pos/__main__.py
tokmor_pos/api.py
tokmor_pos/axes.py
tokmor_pos/coarse_pos8.py
tokmor_pos/ear.py
tokmor_pos/install_parson_mini.py
tokmor_pos/ko_morph_viterbi.py
tokmor_pos/lexicon6.py
tokmor_pos/micro_crf_boundary.py
tokmor_pos/morph_fallback.py
tokmor_pos/morph_pos10.py
tokmor_pos/parson_mini.py
tokmor_pos/resources.py
tokmor_pos/role4.py
tokmor_pos-0.1.21.dist-info/licenses/LICENSE
tokmor_pos-0.1.21.dist-info/METADATA
tokmor_pos-0.1.21.dist-info/WHEEL
tokmor_pos-0.1.21.dist-info/entry_points.txt
tokmor_pos-0.1.21.dist-info/top_level.txt
tokmor_pos-0.1.21.dist-info/RECORD
