Metadata-Version: 2.4
Name: tokmor-pos
Version: 0.1.21
Summary: TokMor POS = ParSon axes(P/A/R/S/O/N) + derived EAR hints (blank allowed).
Author-email: tokmor <tokmor@tokmor.com>
License: MIT License
Project-URL: Homepage, https://github.com/tokmorlab/tokmor
Project-URL: Source, https://github.com/tokmorlab/tokmor
Project-URL: Documentation, https://github.com/tokmorlab/tokmor#readme
Project-URL: Issues, https://github.com/tokmorlab/tokmor/issues
Keywords: nlp,preprocessing,multilingual,ner,tokenization,pos,heuristics
Classifier: Development Status :: 4 - Beta
Classifier: Intended Audience :: Developers
Classifier: Intended Audience :: Science/Research
Classifier: License :: OSI Approved :: MIT License
Classifier: Programming Language :: Python :: 3
Classifier: Programming Language :: Python :: 3.9
Classifier: Programming Language :: Python :: 3.10
Classifier: Programming Language :: Python :: 3.11
Classifier: Programming Language :: Python :: 3.12
Classifier: Topic :: Text Processing :: Linguistic
Requires-Python: >=3.9
License-File: LICENSE
Requires-Dist: tokmor>=1.1.0
Provides-Extra: legacy
Requires-Dist: sklearn-crfsuite>=0.3.6; extra == "legacy"
Dynamic: license-file
